img2ansi/__init__.py
img2ansi/ansi/__init__.py
img2ansi/ansi/ansi.py
img2ansi/ascii/__init__.py
img2ansi/ascii/ascii.py
img2ansi/block/__init__.py
img2ansi/block/block.py
img2ansi/braile/__init__.py
img2ansi/braile/braile.py
img2ansi/braile/characters.py
img2ansi/braile/utilFunctions.py
img2ansi/img2ascii.py
img2ansi/img2block.py
img2ansi/img2braile.py
img2ansi-0.1.2.dist-info/entry_points.txt
img2ansi-0.1.2.dist-info/LICENSE
img2ansi-0.1.2.dist-info/WHEEL
img2ansi-0.1.2.dist-info/METADATA
img2ansi-0.1.2.dist-info/RECORD
