Metadata-Version: 2.1
Name: img2ansi
Version: 0.1.2
Summary: Convert image to ascii/unicode ANSI sequence
License: GPL2
Author: Daniel Bañuelos
Author-email: dax99993@gmail.com
Requires-Python: >=3.9,<4.0
Classifier: License :: Other/Proprietary License
Classifier: Programming Language :: Python :: 3
Classifier: Programming Language :: Python :: 3.10
Classifier: Programming Language :: Python :: 3.9
Requires-Dist: Pillow (>=8.0.0,<9.0.0)
